pg_engine/__init__.py
pg_engine/column.py
pg_engine/database.py
pg_engine/errors.py
pg_engine/events.py
pg_engine/model.py
pg_engine/relation.py
base_pg_engine-0.1.dist-info/METADATA
base_pg_engine-0.1.dist-info/WHEEL
base_pg_engine-0.1.dist-info/top_level.txt
base_pg_engine-0.1.dist-info/RECORD
