Metadata-Version: 2.1
Name: base-pg-engine
Version: 0.1
Requires-Dist: psycopg2
